mrange/__init__.py
mrange/mrange.py
mrange-1.2.dist-info/LICENSE
mrange-1.2.dist-info/METADATA
mrange-1.2.dist-info/WHEEL
mrange-1.2.dist-info/top_level.txt
mrange-1.2.dist-info/RECORD
