Metadata-Version: 2.1
Name: mrange
Version: 1.2
Summary: mrange is used to remove nested range loops
Home-page: https://github.com/Ntropic/mrange/archive/refs/tags/v1.2.tar.gz
Author: Michael Schilling
Author-email: michael@ntropic.de
License: UNKNOWN
Platform: UNKNOWN
Classifier: Programming Language :: Python :: 3
Classifier: License :: OSI Approved :: MIT License
Classifier: Operating System :: OS Independent
Requires-Python: >=3.6
License-File: LICENSE
Requires-Dist: numba
Requires-Dist: numpy
